[{"Month": "2015 Nov", "Sector": "Private", "Growth Rate": 2.3}, {"Month": "2015 Dec", "Sector": "Finance and Business Services", "Growth Rate": 2.5}, {"Month": "2015 Dec", "Sector": "Private", "Growth Rate": 2.1}, {"Month": "2016 Jan", "Sector": "Finance and Business Services", "Growth Rate": 4.9}, {"Month": "2016 Jan", "Sector": "Private", "Growth Rate": 3.0}, {"Month": "2016 Feb", "Sector": "Finance and Business Services", "Growth Rate": -1.4}, {"Month": "2016 Feb", "Sector": "Private", "Growth Rate": 1.0}, {"Month": "2016 Mar", "Sector": "Finance and Business Services", "Growth Rate": 5.2}, {"Month": "2016 Mar", "Sector": "Private", "Growth Rate": 2.4}, {"Month": "2016 Apr", "Sector": "Finance and Business Services", "Growth Rate": 4.0}, {"Month": "2016 Apr", "Sector": "Private", "Growth Rate": 3.3}, {"Month": "2016 May", "Sector": "Finance and Business Services", "Growth Rate": 2.8}, {"Month": "2016 May", "Sector": "Private", "Growth Rate": 2.6}, {"Month": "2016 Jun", "Sector": "Finance and Business Services", "Growth Rate": 3.8}, {"Month": "2016 Jun", "Sector": "Private", "Growth Rate": 2.4}, {"Month": "2016 Jul", "Sector": "Finance and Business Services", "Growth Rate": 3.6}, {"Month": "2016 Jul", "Sector": "Private", "Growth Rate": 2.9}, {"Month": "2016 Aug", "Sector": "Finance and Business Services", "Growth Rate": 1.0}, {"Month": "2016 Aug", "Sector": "Private", "Growth Rate": 2.1}, {"Month": "2016 Sep", "Sector": "Finance and Business Services", "Growth Rate": 1.9}, {"Month": "2016 Sep", "Sector": "Private", "Growth Rate": 2.9}, {"Month": "2016 Oct", "Sector": "Finance and Business Services", "Growth Rate": 1.7}, {"Month": "2016 Oct", "Sector": "Private", "Growth Rate": 3.2}, {"Month": "2016 Nov", "Sector": "Finance and Business Services", "Growth Rate": 2.0}, {"Month": "2016 Nov", "Sector": "Private", "Growth Rate": 3.4}, {"Month": "2016 Dec", "Sector": "Finance and Business Services", "Growth Rate": -0.6}, {"Month": "2016 Dec", "Sector": "Private", "Growth Rate": 1.9}, {"Month": "2017 Jan", "Sector": "Finance and Business Services", "Growth Rate": 0.5}, {"Month": "2017 Jan", "Sector": "Private", "Growth Rate": 1.8}, {"Month": "2017 Feb", "Sector": "Finance and Business Services", "Growth Rate": 1.5}, {"Month": "2017 Feb", "Sector": "Private", "Growth Rate": 2.7}, {"Month": "2017 Mar", "Sector": "Finance and Business Services", "Growth Rate": 3.6}, {"Month": "2017 Mar", "Sector": "Private", "Growth Rate": 2.8}, {"Month": "2017 Apr", "Sector": "Finance and Business Services", "Growth Rate": -0.5}, {"Month": "2017 Apr", "Sector": "Private", "Growth Rate": 1.4}, {"Month": "2017 May", "Sector": "Finance and Business Services", "Growth Rate": 2.1}, {"Month": "2017 May", "Sector": "Private", "Growth Rate": 2.1}, {"Month": "2017 Jun", "Sector": "Finance and Business Services", "Growth Rate": 4.3}, {"Month": "2017 Jun", "Sector": "Private", "Growth Rate": 3.4}, {"Month": "2017 Jul", "Sector": "Finance and Business Services", "Growth Rate": 1.2}, {"Month": "2017 Jul", "Sector": "Private", "Growth Rate": 1.6}, {"Month": "2017 Aug", "Sector": "Finance and Business Services", "Growth Rate": 3.2}, {"Month": "2017 Aug", "Sector": "Private", "Growth Rate": 2.6}, {"Month": "2017 Sep", "Sector": "Finance and Business Services", "Growth Rate": 4.8}, {"Month": "2017 Sep", "Sector": "Private", "Growth Rate": 3.3}, {"Month": "2017 Oct", "Sector": "Finance and Business Services", "Growth Rate": 2.9}, {"Month": "2017 Oct", "Sector": "Private", "Growth Rate": 2.6}, {"Month": "2017 Nov", "Sector": "Finance and Business Services", "Growth Rate": 2.3}, {"Month": "2017 Nov", "Sector": "Private", "Growth Rate": 2.6}, {"Month": "2017 Dec", "Sector": "Finance and Business Services", "Growth Rate": 4.4}, {"Month": "2017 Dec", "Sector": "Private", "Growth Rate": 3.5}, {"Month": "2018 Jan", "Sector": "Finance and Business Services", "Growth Rate": 2.7}, {"Month": "2018 Jan", "Sector": "Private", "Growth Rate": 2.8}, {"Month": "2018 Feb", "Sector": "Finance and Business Services", "Growth Rate": 2.8}, {"Month": "2018 Feb", "Sector": "Private", "Growth Rate": 2.2}, {"Month": "2018 Mar", "Sector": "Finance and Business Services", "Growth Rate": 1.0}, {"Month": "2018 Mar", "Sector": "Private", "Growth Rate": 2.7}, {"Month": "2018 Apr", "Sector": "Finance and Business Services", "Growth Rate": 2.6}, {"Month": "2018 Apr", "Sector": "Private", "Growth Rate": 2.7}, {"Month": "2018 May", "Sector": "Finance and Business Services", "Growth Rate": 0.7}, {"Month": "2018 May", "Sector": "Private", "Growth Rate": 2.6}, {"Month": "2018 Jun", "Sector": "Finance and Business Services", "Growth Rate": 0.6}, {"Month": "2018 Jun", "Sector": "Private", "Growth Rate": 2.1}, {"Month": "2018 Jul", "Sector": "Finance and Business Services", "Growth Rate": 3.5}, {"Month": "2018 Jul", "Sector": "Private", "Growth Rate": 3.3}, {"Month": "2018 Aug", "Sector": "Finance and Business Services", "Growth Rate": 2.3}, {"Month": "2018 Aug", "Sector": "Private", "Growth Rate": 3.3}, {"Month": "2018 Sep", "Sector": "Finance and Business Services", "Growth Rate": 1.7}, {"Month": "2018 Sep", "Sector": "Private", "Growth Rate": 2.9}, {"Month": "2018 Oct", "Sector": "Finance and Business Services", "Growth Rate": 4.8}, {"Month": "2018 Oct", "Sector": "Private", "Growth Rate": 4.6}, {"Month": "2018 Nov", "Sector": "Finance and Business Services", "Growth Rate": 4.3}, {"Month": "2018 Nov", "Sector": "Private", "Growth Rate": 3.4}, {"Month": "2018 Dec", "Sector": "Finance and Business Services", "Growth Rate": 3.1}, {"Month": "2018 Dec", "Sector": "Private", "Growth Rate": 3.4}, {"Month": "2019 Jan", "Sector": "Finance and Business Services", "Growth Rate": 5.3}, {"Month": "2019 Jan", "Sector": "Private", "Growth Rate": 4.3}, {"Month": "2019 Feb", "Sector": "Finance and Business Services", "Growth Rate": 2.9}, {"Month": "2019 Feb", "Sector": "Private", "Growth Rate": 3.4}, {"Month": "2019 Mar", "Sector": "Finance and Business Services", "Growth Rate": 3.2}, {"Month": "2019 Mar", "Sector": "Private", "Growth Rate": 2.5}, {"Month": "2019 Apr", "Sector": "Finance and Business Services", "Growth Rate": 3.7}, {"Month": "2019 Apr", "Sector": "Private", "Growth Rate": 3.4}, {"Month": "2019 May", "Sector": "Finance and Business Services", "Growth Rate": 5.4}, {"Month": "2019 May", "Sector": "Private", "Growth Rate": 4.1}, {"Month": "2019 Jun", "Sector": "Finance and Business Services", "Growth Rate": 5.1}, {"Month": "2019 Jun", "Sector": "Private", "Growth Rate": 3.9}, {"Month": "2019 Jul", "Sector": "Finance and Business Services", "Growth Rate": 3.9}, {"Month": "2019 Jul", "Sector": "Private", "Growth Rate": 3.9}, {"Month": "2019 Aug", "Sector": "Finance and Business Services", "Growth Rate": 4.2}, {"Month": "2019 Aug", "Sector": "Private", "Growth Rate": 3.4}, {"Month": "2019 Sep", "Sector": "Finance and Business Services", "Growth Rate": 5.3}, {"Month": "2019 Sep", "Sector": "Private", "Growth Rate": 4.0}, {"Month": "2019 Oct", "Sector": "Finance and Business Services", "Growth Rate": 3.5}, {"Month": "2019 Oct", "Sector": "Private", "Growth Rate": 2.2}, {"Month": "2019 Nov", "Sector": "Finance and Business Services", "Growth Rate": 4.1}, {"Month": "2019 Nov", "Sector": "Private", "Growth Rate": 3.4}, {"Month": "2019 Dec", "Sector": "Finance and Business Services", "Growth Rate": 3.5}, {"Month": "2019 Dec", "Sector": "Private", "Growth Rate": 2.6}, {"Month": "2020 Jan", "Sector": "Finance and Business Services", "Growth Rate": 3.6}, {"Month": "2020 Jan", "Sector": "Private", "Growth Rate": 3.5}, {"Month": "2020 Feb", "Sector": "Finance and Business Services", "Growth Rate": 2.3}, {"Month": "2020 Feb", "Sector": "Private", "Growth Rate": 2.1}, {"Month": "2020 Mar", "Sector": "Finance and Business Services", "Growth Rate": -0.8}, {"Month": "2020 Mar", "Sector": "Private", "Growth Rate": 0.6}, {"Month": "2020 Apr", "Sector": "Finance and Business Services", "Growth Rate": 0.3}, {"Month": "2020 Apr", "Sector": "Private", "Growth Rate": -1.9}, {"Month": "2020 May", "Sector": "Finance and Business Services", "Growth Rate": -0.1}, {"Month": "2020 May", "Sector": "Private", "Growth Rate": -2.5}, {"Month": "2020 Jun", "Sector": "Finance and Business Services", "Growth Rate": -3.1}, {"Month": "2020 Jun", "Sector": "Private", "Growth Rate": -2.9}, {"Month": "2020 Jul", "Sector": "Finance and Business Services", "Growth Rate": -0.3}, {"Month": "2020 Jul", "Sector": "Private", "Growth Rate": -1.0}, {"Month": "2020 Aug", "Sector": "Finance and Business Services", "Growth Rate": 4.2}, {"Month": "2020 Aug", "Sector": "Private", "Growth Rate": 1.7}, {"Month": "2020 Sep", "Sector": "Finance and Business Services", "Growth Rate": 4.3}, {"Month": "2020 Sep", "Sector": "Private", "Growth Rate": 2.0}, {"Month": "2020 Oct", "Sector": "Finance and Business Services", "Growth Rate": 6.2}, {"Month": "2020 Oct", "Sector": "Private", "Growth Rate": 3.7}, {"Month": "2020 Nov", "Sector": "Finance and Business Services", "Growth Rate": 7.9}, {"Month": "2020 Nov", "Sector": "Private", "Growth Rate": 5.1}, {"Month": "2020 Dec", "Sector": "Finance and Business Services", "Growth Rate": 7.9}, {"Month": "2020 Dec", "Sector": "Private", "Growth Rate": 5.9}, {"Month": "2021 Jan", "Sector": "Finance and Business Services", "Growth Rate": 8.3}, {"Month": "2021 Jan", "Sector": "Private", "Growth Rate": 4.2}, {"Month": "2021 Feb", "Sector": "Finance and Business Services", "Growth Rate": 3.5}, {"Month": "2021 Feb", "Sector": "Private", "Growth Rate": 3.8}, {"Month": "2021 Mar", "Sector": "Finance and Business Services", "Growth Rate": 5.2}, {"Month": "2021 Mar", "Sector": "Private", "Growth Rate": 4.2}, {"Month": "2021 Apr", "Sector": "Finance and Business Services", "Growth Rate": 12.8}, {"Month": "2021 Apr", "Sector": "Private", "Growth Rate": 10.1}, {"Month": "2021 May", "Sector": "Finance and Business Services", "Growth Rate": 12.5}, {"Month": "2021 May", "Sector": "Private", "Growth Rate": 10.6}, {"Month": "2021 Jun", "Sector": "Finance and Business Services", "Growth Rate": 12.5}, {"Month": "2021 Jun", "Sector": "Private", "Growth Rate": 10.4}, {"Month": "2021 Jul ", "Sector": "Finance and Business Services", "Growth Rate": 12.0}, {"Month": "2021 Jul ", "Sector": "Private", "Growth Rate": 8.2}, {"Month": "2021 Aug", "Sector": "Finance and Business Services", "Growth Rate": 8.8}, {"Month": "2021 Aug", "Sector": "Private", "Growth Rate": 6.5}, {"Month": "2021 Sep", "Sector": "Finance and Business Services", "Growth Rate": 7.6}, {"Month": "2021 Sep", "Sector": "Private", "Growth Rate": 5.2}, {"Month": "2021 Oct", "Sector": "Finance and Business Services", "Growth Rate": 7.4}, {"Month": "2021 Oct", "Sector": "Private", "Growth Rate": 4.8}, {"Month": "2021 Nov", "Sector": "Finance and Business Services", "Growth Rate": 5.5}, {"Month": "2021 Nov", "Sector": "Private", "Growth Rate": 3.8}, {"Month": "2021 Dec", "Sector": "Finance and Business Services", "Growth Rate": 14.2}, {"Month": "2021 Dec", "Sector": "Private", "Growth Rate": 6.9}, {"Month": "2022 Jan", "Sector": "Finance and Business Services", "Growth Rate": 6.5}, {"Month": "2022 Jan", "Sector": "Private", "Growth Rate": 5.9}, {"Month": "2022 Feb", "Sector": "Finance and Business Services", "Growth Rate": 9.6}, {"Month": "2022 Feb", "Sector": "Private", "Growth Rate": 5.9}, {"Month": "2022 Mar", "Sector": "Finance and Business Services", "Growth Rate": 16.1}, {"Month": "2022 Mar", "Sector": "Private", "Growth Rate": 12.0}, {"Month": "2022 Apr", "Sector": "Finance and Business Services", "Growth Rate": 5.2}, {"Month": "2022 Apr", "Sector": "Private", "Growth Rate": 5.7}, {"Month": "2022 May", "Sector": "Finance and Business Services", "Growth Rate": 4.0}, {"Month": "2022 May", "Sector": "Private", "Growth Rate": 4.8}, {"Month": "2022 Jun", "Sector": "Finance and Business Services", "Growth Rate": 9.2}, {"Month": "2022 Jun", "Sector": "Private", "Growth Rate": 7.4}, {"Month": "2022 Jul", "Sector": "Finance and Business Services", "Growth Rate": 5.4}, {"Month": "2022 Jul", "Sector": "Private", "Growth Rate": 6.6}, {"Month": "2022 Aug", "Sector": "Finance and Business Services", "Growth Rate": 6.5}, {"Month": "2022 Aug", "Sector": "Private", "Growth Rate": 6.9}, {"Month": "2022 Sep", "Sector": "Finance and Business Services", "Growth Rate": 6.2}, {"Month": "2022 Sep", "Sector": "Private", "Growth Rate": 6.8}]
